apikeylogger/__init__.py
apikeylogger/decorators.py
apikeylogger/mock.py
apikeylogger/pricing.py
apikeylogger/tiktoken_count.py
apikeylogger-1.1.1.dist-info/LICENSE
apikeylogger-1.1.1.dist-info/METADATA
apikeylogger-1.1.1.dist-info/WHEEL
apikeylogger-1.1.1.dist-info/top_level.txt
apikeylogger-1.1.1.dist-info/RECORD
