Metadata-Version: 2.1
Name: apikeylogger
Version: 1.1.1
Summary: This library allows you to log the OpenAI api usage *by key* without having to change your code
Home-page: https://github.com/federicoromeo/apikeylogger
Author: Federico Romeo
Author-email: federico.romeo.98@gmail.com
License: MIT
Project-URL: Source, https://github.com/federicoromeo/apikeylogger
Keywords: openai,apikey,api,logger,tracker
Platform: UNKNOWN
Requires-Python: >=3.6
License-File: LICENSE
Requires-Dist: beautifulsoup4
Requires-Dist: openai >=1.6.0
Requires-Dist: python-dotenv >=0.18.0
Requires-Dist: tiktoken
